[
  {
    "start": 17,
    "width": 6.5308777461081435,
    "center": 21,
    "series_idx": 2,
    "control_points": [
      0.8212900990432618,
      0.9392639672384132,
      0.40599701062474747,
      0.05285123706599215,
      0.515630449502381
    ],
    "transform_type": "sorted",
    "pattern_id": 1
  },
  {
    "start": 21,
    "width": 2.997185797719962,
    "center": 22,
    "series_idx": 0,
    "control_points": [
      0.14642583007706955,
      0.5773331966611175,
      0.029079054807933824,
      0.5038956167068582,
      0.9075575951699999
    ],
    "transform_type": "reciprocal",
    "pattern_id": 2
  },
  {
    "start": 0,
    "width": 14.304558004348529,
    "center": 5,
    "series_idx": 0,
    "control_points": [
      0.808710696857684,
      0.9480906006456329,
      0.4326227169528506,
      0.0971834963218341,
      0.44707168784723195
    ],
    "transform_type": "reciprocal",
    "pattern_id": 3
  },
  {
    "start": 5,
    "width": 2.0147044000379397,
    "center": 6,
    "series_idx": 0,
    "control_points": [
      0.6763291557119414,
      0.6379675188525329,
      0.48187415937431133,
      0.3180075804431828,
      0.2513808742270375
    ],
    "transform_type": "raw",
    "pattern_id": 4
  },
  {
    "start": 0,
    "width": 7.337792969173964,
    "center": 2,
    "series_idx": 1,
    "control_points": [
      0.0291639843227951,
      0.6131449301511253,
      0.4353170376049673,
      0.6853987285121038,
      0.6429520780336542
    ],
    "transform_type": "log1p",
    "pattern_id": 5
  },
  {
    "start": 18,
    "width": 2.046933882653846,
    "center": 19,
    "series_idx": 0,
    "control_points": [
      0.3829327453128335,
      0.6396480427727838,
      0.5768435391318197,
      0.44584475784590105,
      0.3973805110115396
    ],
    "transform_type": "log1p",
    "pattern_id": 6
  },
  {
    "start": 0,
    "width": 12.19077938600217,
    "center": 6,
    "series_idx": 1,
    "control_points": [
      0.9886031661946268,
      0.6029286774916027,
      0.978092594635437,
      0.23777389116216885,
      0.8817999986834661
    ],
    "transform_type": "abs",
    "pattern_id": 7
  },
  {
    "start": 9,
    "width": 12.601863089197503,
    "center": 15,
    "series_idx": 2,
    "control_points": [
      0.49643742447000083,
      0.8329791335121087,
      0.7774212860201379,
      0.2466042862683251,
      0.2215232509369517
    ],
    "transform_type": "abs",
    "pattern_id": 8
  },
  {
    "start": 3,
    "width": 21.02102272086249,
    "center": 14,
    "series_idx": 1,
    "control_points": [
      0.2792875823841926,
      0.06422159920557569,
      0.35167585188395956,
      0.11128953769825467,
      0.055308825617267465
    ],
    "transform_type": "sorted",
    "pattern_id": 9
  },
  {
    "start": 0,
    "width": 21.15582145635078,
    "center": 5,
    "series_idx": 1,
    "control_points": [
      0.8588562598688161,
      0.6482504309380158,
      0.09134202857922413,
      0.9204557236145593,
      0.6051230670644812
    ],
    "transform_type": "abs",
    "pattern_id": 10
  },
  {
    "start": 5,
    "width": 8.184754572773821,
    "center": 9,
    "series_idx": 0,
    "control_points": [
      0.10495673617140755,
      0.4461608381337173,
      0.2283672129342612,
      0.9906590356774003,
      0.721960122415449
    ],
    "transform_type": "raw",
    "pattern_id": 11
  },
  {
    "start": 8,
    "width": 14.96343706572647,
    "center": 15,
    "series_idx": 0,
    "control_points": [
      0.9227766777972976,
      0.02018986972021597,
      0.8660444157632998,
      0.23203508897723857,
      0.7890219451911897
    ],
    "transform_type": "reciprocal",
    "pattern_id": 12
  },
  {
    "start": 0,
    "width": 16.73773320363015,
    "center": 3,
    "series_idx": 0,
    "control_points": [
      0.7502600908730553,
      0.5567935100514307,
      0.734311776196895,
      0.6263999355674207,
      0.5836544301831871
    ],
    "transform_type": "abs",
    "pattern_id": 13
  }
]