[
  {
    "width": 2,
    "series_idx": 0,
    "pattern_params": {
      "c0": 0.12107034499253777,
      "c1": 0.7263988391674966,
      "c2": 0.7536048637037374
    },
    "pattern_type": "bezier",
    "transform_type": "preemph99",
    "start": 5,
    "end": 22,
    "distance_metric": "mse",
    "sliding_window": true,
    "pattern_id": 1
  },
  {
    "width": 20,
    "series_idx": 0,
    "pattern_params": {
      "c0": -0.5078666981850423,
      "c1": 0.2138299793746659,
      "c2": -0.07038986455134975
    },
    "pattern_type": "bezier",
    "transform_type": "abs",
    "start": 4,
    "end": 4,
    "distance_metric": "mse",
    "sliding_window": true,
    "pattern_id": 2
  },
  {
    "width": 10,
    "series_idx": 2,
    "pattern_params": {
      "c0": -0.7887028077480522,
      "c1": 0.5804269338335709,
      "c2": 0.9091005822700234
    },
    "pattern_type": "bezier",
    "transform_type": "reciprocal",
    "start": 0,
    "end": 14,
    "distance_metric": "mse",
    "sliding_window": true,
    "pattern_id": 3
  },
  {
    "width": 24,
    "series_idx": 0,
    "pattern_params": {
      "c0": -0.8723315328037868,
      "c1": -0.6680368012392626,
      "c2": -0.8352558122746397
    },
    "pattern_type": "bezier",
    "transform_type": "preemph99",
    "start": 0,
    "end": 0,
    "distance_metric": "mse",
    "sliding_window": true,
    "pattern_id": 4
  },
  {
    "width": 3,
    "series_idx": 1,
    "pattern_params": {
      "c0": -0.5509889591221457,
      "c1": 0.12376232574600962,
      "c2": -0.11186379401285543
    },
    "pattern_type": "bezier",
    "transform_type": "sorted",
    "start": 2,
    "end": 11,
    "distance_metric": "mse",
    "sliding_window": true,
    "pattern_id": 5
  },
  {
    "width": 4,
    "series_idx": 0,
    "pattern_params": {
      "c0": -0.7681225288134538,
      "c1": -0.7939180649702965,
      "c2": -0.127123732924993
    },
    "pattern_type": "bezier",
    "transform_type": "diff",
    "start": 1,
    "end": 14,
    "distance_metric": "mse",
    "sliding_window": true,
    "pattern_id": 6
  },
  {
    "width": 3,
    "series_idx": 0,
    "pattern_params": {
      "c0": 0.9576738228521011,
      "c1": -0.9206551529175109,
      "c2": -0.7930679458841144
    },
    "pattern_type": "bezier",
    "transform_type": "preemph99",
    "start": 7,
    "end": 21,
    "distance_metric": "mse",
    "sliding_window": true,
    "pattern_id": 7
  },
  {
    "width": 24,
    "series_idx": 2,
    "pattern_params": {
      "c0": 0.006304568607637673,
      "c1": -0.05627038974783066,
      "c2": -0.49327463520943726
    },
    "pattern_type": "bezier",
    "transform_type": "abs",
    "start": 0,
    "end": 0,
    "distance_metric": "mse",
    "sliding_window": true,
    "pattern_id": 8
  },
  {
    "width": 10,
    "series_idx": 1,
    "pattern_params": {
      "c0": 0.570648697932101,
      "c1": -0.6790946394609372,
      "c2": 0.947432794909544
    },
    "pattern_type": "bezier",
    "transform_type": "diff",
    "start": 1,
    "end": 14,
    "distance_metric": "mse",
    "sliding_window": true,
    "pattern_id": 9
  },
  {
    "width": 2,
    "series_idx": 2,
    "pattern_params": {
      "c0": -0.7915564540515736,
      "c1": 0.0892406799587022,
      "c2": 0.7096345692534419
    },
    "pattern_type": "bezier",
    "transform_type": "diff",
    "start": 3,
    "end": 22,
    "distance_metric": "mse",
    "sliding_window": true,
    "pattern_id": 10
  },
  {
    "width": 12,
    "series_idx": 1,
    "pattern_params": {
      "c0": 0.8511348224359051,
      "c1": 0.27305278461068255,
      "c2": -0.5555251164587613
    },
    "pattern_type": "bezier",
    "transform_type": "sorted",
    "start": 5,
    "end": 12,
    "distance_metric": "mse",
    "sliding_window": true,
    "pattern_id": 11
  },
  {
    "width": 2,
    "series_idx": 0,
    "pattern_params": {
      "c0": -0.9629634700897597,
      "c1": 0.927662032305644,
      "c2": -0.5960253685515586
    },
    "pattern_type": "bezier",
    "transform_type": "preemph99",
    "start": 2,
    "end": 20,
    "distance_metric": "mse",
    "sliding_window": true,
    "pattern_id": 12
  }
]